<metadata>
<remove-node path="/api/package[@name='com.esri.android.map.popup']" />
<remove-node path="/api/package[@name='com.esri.core.geometry']/class[@name='Geometry']/field[@name='m_description']" />
<remove-node path="/api/package[@name='com.esri.core.geometry']/class[@name='MultiPath']/field[@name='m_impl']" />
<remove-node path="/api/package[starts-with(@name,'com.esri.core.internal')]" />
<remove-node path="/api/package[@name='com.esri.core.portal']" />
<!--<remove-node path="/api/package[@name='com.esri.core.renderer']/class[@name='MultipartColorRamp']" />-->
<!--<remove-node path="/api/package[@name='com.esri.core.symbol']/class[@name='PictureMarkerSymbol']/constructor/parameter[@type='java.lang.String']/.." />-->
<attr path="/api/package[@name='com.esri.core.geometry']/class[@name='MultiPath']" name="extends">com.esri.core.geometry.Geometry</attr>
<attr path="/api/package[@name='com.esri.core.geometry']/class[@name='MultiPath']" name="extends-generic-aware">com.esri.core.geometry.Geometry</attr>
<attr path="/api/package[@name='com.esri.core.geometry']/class[@name='MultiPoint']" name="extends">com.esri.core.geometry.Geometry</attr>
<attr path="/api/package[@name='com.esri.core.geometry']/class[@name='MultiPoint']" name="extends-generic-aware">com.esri.core.geometry.Geometry</attr>
<attr path="/api/package[@name='com.esri.core.tasks.ags.geocode']/class[@name='LocatorGeocodeResult']" name="extends">java.lang.Object</attr>
<attr path="/api/package[@name='com.esri.core.tasks.ags.geocode']/class[@name='LocatorGeocodeResult']" name="extends-generic-aware">java.lang.Object</attr>
<attr path="/api/package[@name='com.esri.core.tasks.ags.geocode']/class[@name='LocatorReverseGeocodeResult']" name="extends">java.lang.Object</attr>
<attr path="/api/package[@name='com.esri.core.tasks.ags.geocode']/class[@name='LocatorReverseGeocodeResult']" name="extends-generic-aware">java.lang.Object</attr>
<attr path="/api/package[@name='com.esri.core.tasks.geocode']/class[@name='LocatorGeocodeResult']" name="extends">java.lang.Object</attr>
<attr path="/api/package[@name='com.esri.core.tasks.geocode']/class[@name='LocatorGeocodeResult']" name="extends-generic-aware">java.lang.Object</attr>
<attr path="/api/package[@name='com.esri.core.tasks.geocode']/class[@name='LocatorReverseGeocodeResult']" name="extends">java.lang.Object</attr>
<attr path="/api/package[@name='com.esri.core.tasks.geocode']/class[@name='LocatorReverseGeocodeResult']" name="extends-generic-aware">java.lang.Object</attr>
<attr path="/api/package[@name='com.esri.core.geometry']/class[@name='Geometry']/method[@name='getType']" name="managedName">getGeometryType</attr>
<attr path="/api/package[@name='com.esri.core.geometry']/class[@name='Envelope']/method[@name='getType']" name="managedName">getGeometryType</attr>
<attr path="/api/package[@name='com.esri.core.geometry']/class[@name='Line']/method[@name='getType']" name="managedName">getGeometryType</attr>
<attr path="/api/package[@name='com.esri.core.geometry']/class[@name='MultiPoint']/method[@name='getType']" name="managedName">getGeometryType</attr>
<attr path="/api/package[@name='com.esri.core.geometry']/class[@name='Point']/method[@name='getType']" name="managedName">getGeometryType</attr>
<attr path="/api/package[@name='com.esri.core.geometry']/class[@name='Polygon']/method[@name='getType']" name="managedName">getGeometryType</attr>
<attr path="/api/package[@name='com.esri.core.geometry']/class[@name='Polyline']/method[@name='getType']" name="managedName">getGeometryType</attr>
<attr path="/api/package[@name='com.esri.core.symbol']/class[@name='MultiLayerSymbol']/method[@name='copy']" name="return">com.esri.core.symbol.Symbol</attr>
<attr path="/api/package[@name='com.esri.core.tasks.ags.query']/class[@name='OutStatistics']/method[@name='getType']" name="managedName">getStatisticsType</attr>
<add-node path="/api/package[@name='com.esri.core.ogc.wmts']/class[@name='WMTSTileMatrixSet.TileMatrixComparator'][implements[@name='java.lang.Comparable']]">
  <method name="compareTo" return="int" abstract="false" native="false" synchronized="false" static="false" final="false" deprecated="not deprecated" visibility="public">
    <parameter name="o" type="java.lang.Object" />
  </method>
</add-node>
<add-node path="/api/package[@name='com.esri.core.ogc.wmts']/class[@name='WMTSTileMatrixSet.TileMatrixComparator'][implements[@name='java.util.Comparator']]">
  <method name="compare" return="int" abstract="false" native="false" synchronized="false" static="false" final="false" deprecated="not deprecated" visibility="public">
    <parameter name="o1" type="java.lang.Object" />
    <parameter name="o2" type="java.lang.Object" />
  </method>
</add-node>
<attr path="/api/package[@name='com.esri.core.map.ogc.kml']/class[@name='KmlNode']/method[@name='getType' and count(parameter)=0]" name="managedName">GetKmlNodeType</attr>
<attr path="/api/package[@name='com.esri.core.map.ogc.kml']/class[@name='KmlNode.Type']" name="managedName">KmlNodeType</attr>
<attr path="/api/package[@name='com.esri.core.tasks.query']/class[@name='OutStatistics']/method[@name='getType' and count(parameter)=0]" name="managedName">GetOutStatisticsType</attr>
<attr path="/api/package[@name='com.esri.core.tasks.query']/class[@name='OutStatistics.Type']" name="managedName">OutStatisticsType</attr>
</metadata>

<!--<metadata>
  <remove-node path="/api/package[starts-with(@name,'com.esri.core.internal')]" />
  --><!--<remove-node path="/api/package[@name='com.esri.core.symbol']/class[@name='PictureMarkerSymbol']/constructor/parameter[@type='java.lang.String']/.." />--><!--
  --><!--<remove-node path="/api/package[@name='com.esri.android.map.popup']/class[@name='ArcGISMediaAdapter.MediaAdapterListener']" />
  <remove-node path="/api/package[@name='com.esri.android.map.popup']/class[@name='ArcGISMediaAdapter.MediaView.LoadStatusListenerImplementor']" />--><!--
 <remove-node path="/api/package[@name='com.esri.android.map.popup']" />

  <attr path="/api/package[@name='com.esri.core.tasks.ags.geocode']/class[@name='LocatorGeocodeResult']" name="extends">java.lang.Object</attr>
  <attr path="/api/package[@name='com.esri.core.tasks.ags.geocode']/class[@name='LocatorGeocodeResult']" name="extends-generic-aware">java.lang.Object</attr>

  <attr path="/api/package[@name='com.esri.core.tasks.ags.geocode']/class[@name='LocatorReverseGeocodeResult']" name="extends">java.lang.Object</attr>
  <attr path="/api/package[@name='com.esri.core.tasks.ags.geocode']/class[@name='LocatorReverseGeocodeResult']" name="extends-generic-aware">java.lang.Object</attr>
  
  <attr path="/api/package[@name='com.esri.core.tasks.geocode']/class[@name='LocatorGeocodeResult']" name="extends">java.lang.Object</attr>
  <attr path="/api/package[@name='com.esri.core.tasks.geocode']/class[@name='LocatorGeocodeResult']" name="extends-generic-aware">java.lang.Object</attr>
  
  <attr path="/api/package[@name='com.esri.core.tasks.geocode']/class[@name='LocatorReverseGeocodeResult']" name="extends">java.lang.Object</attr>
  <attr path="/api/package[@name='com.esri.core.tasks.geocode']/class[@name='LocatorReverseGeocodeResult']" name="extends-generic-aware">java.lang.Object</attr>
  
  <attr path="/api/package[@name='com.esri.core.geometry']/class[@name='Geometry']/method[@name='getType']" name="managedName">getGeometryType</attr>
  <attr path="/api/package[@name='com.esri.core.geometry']/class[@name='Envelope']/method[@name='getType']" name="managedName">getGeometryType</attr>
  <attr path="/api/package[@name='com.esri.core.geometry']/class[@name='Line']/method[@name='getType']" name="managedName">getGeometryType</attr>
  <attr path="/api/package[@name='com.esri.core.geometry']/class[@name='MultiPoint']/method[@name='getType']" name="managedName">getGeometryType</attr>
  <attr path="/api/package[@name='com.esri.core.geometry']/class[@name='Point']/method[@name='getType']" name="managedName">getGeometryType</attr>
  <attr path="/api/package[@name='com.esri.core.geometry']/class[@name='Polygon']/method[@name='getType']" name="managedName">getGeometryType</attr>
  <attr path="/api/package[@name='com.esri.core.geometry']/class[@name='Polyline']/method[@name='getType']" name="managedName">getGeometryType</attr>
  <attr path="/api/package[@name='com.esri.core.symbol']/class[@name='MultiLayerSymbol']/method[@name='copy']" name="return">com.esri.core.symbol.Symbol</attr>
  <attr path="/api/package[@name='com.esri.core.tasks.ags.query']/class[@name='OutStatistics']/method[@name='getType']" name="managedName">getStatisticsType</attr>
  <attr path="/api/package[@name='com.esri.core.geometry']/class[@name='MultiPath']" name="extends">com.esri.core.geometry.Geometry</attr>
  <attr path="/api/package[@name='com.esri.core.geometry']/class[@name='MultiPath']" name="extends-generic-aware">com.esri.core.geometry.Geometry</attr>
  <attr path="/api/package[@name='com.esri.core.geometry']/class[@name='MultiPoint']" name="extends">com.esri.core.geometry.Geometry</attr>
  <attr path="/api/package[@name='com.esri.core.geometry']/class[@name='MultiPoint']" name="extends-generic-aware">com.esri.core.geometry.Geometry</attr>

  <add-node path="/api/package[@name='com.esri.core.ogc.wmts']/class[@name='WMTSTileMatrixSet.TileMatrixComparator'][implements[@name='java.lang.Comparable']]">
    <method name="compareTo" return="int" abstract="false" native="false" synchronized="false" static="false" final="false" deprecated="not deprecated" visibility="public">
      <parameter name="o" type="java.lang.Object" />
    </method>
  </add-node>
  <add-node path="/api/package[@name='com.esri.core.ogc.wmts']/class[@name='WMTSTileMatrixSet.TileMatrixComparator'][implements[@name='java.util.Comparator']]">
    <method name="compare" return="int" abstract="false" native="false" synchronized="false" static="false" final="false" deprecated="not deprecated" visibility="public">
      <parameter name="o1" type="java.lang.Object" />
      <parameter name="o2" type="java.lang.Object" />
    </method>
  </add-node>
  <attr path="/api/package[@name='com.esri.core.map.ogc.kml']/class[@name='KmlNode']/method[@name='getType' and count(parameter)=0]" name="managedName">GetKmlNodeType</attr>
  <attr path="/api/package[@name='com.esri.core.map.ogc.kml']/class[@name='KmlNode.Type']" name="managedName">KmlNodeType</attr>
  <attr path="/api/package[@name='com.esri.core.tasks.query']/class[@name='OutStatistics']/method[@name='getType' and count(parameter)=0]" name="managedName">GetOutStatisticsType</attr>
  <attr path="/api/package[@name='com.esri.core.tasks.query']/class[@name='OutStatistics.Type']" name="managedName">OutStatisticsType</attr>


  <attr path="/api/package[@name='com.esri.core.map.ogc.kml']/class[@name='KmlNode.Type']" name="managedName">KmlNodeType</attr>
  <attr path="/api/package[@name='com.esri.core.portal']/class[@name='WebMapLayer.Type']" name="managedName">WebMapLayerType</attr>
  <attr path="/api/package[@name='com.esri.android.map.popup']/class[@name='ArcGISMediaAdapter.MediaView.STATUS']" name="visibility">public</attr>
  <attr path="/api/package[@name='com.esri.android.map.popup']/class[@name='ArcGISEditAttributesAdapter.RangeSpinnerAdapter']/method[@name='getItem' and count(parameter)=1]" name="managedName">GetItem2</attr>

  <attr path="/api/package[@name='com.esri.core.geometry']/class[@name='VertexDescription']" name="visibility">public</attr>
  <attr path="/api/package[@name='com.esri.core.geometry']/class[@name='MultiPathImpl']" name="visibility">public</attr>

  <attr path="/api/package[@name='com.esri.core.geometry']/class[@name='MultiVertexGeometryImpl']" name="visibility">public</attr>
  <attr path="/api/package[@name='com.esri.core.geometry']/class[@name='AttributeStreamOfInt8']" name="visibility">public</attr>
  <attr path="/api/package[@name='com.esri.core.geometry']/class[@name='AttributeStreamOfInt32']" name="visibility">public</attr>
  <attr path="/api/package[@name='com.esri.core.geometry']/class[@name='AttributeStreamOfDbl']" name="visibility">public</attr>
  <attr path="/api/package[@name='com.esri.core.geometry']/class[@name='AttributeStreamBase']" name="visibility">public</attr>
  <attr path="/api/package[@name='com.esri.core.geometry']/class[@name='MultiVertexGeometry']" name="visibility">public</attr>
  <attr path="/api/package[@name='com.esri.core.geometry']/class[@name='MultiPathImpl']/method[@name='_notifyModifiedAllImpl']" name="visibility">protected</attr>
</metadata>-->
